LICENSE
src/.env
src/__init__.py
src/article.py
src/arxiv_script.py
src/path_control.py
src/retrieve.py
arxiv_script-0.2.0.dist-info/entry_points.txt
arxiv_script-0.2.0.dist-info/LICENSE
arxiv_script-0.2.0.dist-info/WHEEL
arxiv_script-0.2.0.dist-info/METADATA
arxiv_script-0.2.0.dist-info/RECORD
