Metadata-Version: 2.1
Name: arxiv-script
Version: 0.2.0
Summary: Command line tool to handle arXiv articles and their BibTeX entries.
Home-page: https://github.com/flrnbc/arxiv_script
License: MIT
Keywords: arxiv,python,click
Author: Florian Beck
Author-email: flrn.beck@gmail.com
Requires-Python: >=3.6.1,<4
Classifier: License :: OSI Approved :: MIT License
Classifier: Programming Language :: Python :: 3
Classifier: Programming Language :: Python :: 3.7
Classifier: Programming Language :: Python :: 3.8
Classifier: Programming Language :: Python :: 3.9
Requires-Dist: click (>=7.1.2,<8.0.0)
Requires-Dist: lxml (>=4.6.3,<5.0.0)
Requires-Dist: python-dotenv (>=0.17.0,<0.18.0)
Requires-Dist: requests (>=2.25.1,<3.0.0)
Requires-Dist: urllib3 (>=1.23)
Project-URL: Repository, https://github.com/flrnbc/arxiv_script
